pdfwm/__init__.py
pdfwm/cli.py
pdfwm/core.py
pdfwm/py.typed
pdfwm-0.2.0.dist-info/licenses/LICENSE
pdfwm-0.2.0.dist-info/METADATA
pdfwm-0.2.0.dist-info/WHEEL
pdfwm-0.2.0.dist-info/entry_points.txt
pdfwm-0.2.0.dist-info/top_level.txt
pdfwm-0.2.0.dist-info/RECORD
