Metadata-Version: 2.4
Name: pdfwm
Version: 0.2.0
Summary: A Python library and CLI tool for adding text watermarks to PDF files
Author-email: oclero <oclero@pm.me>
License: MIT
Project-URL: Homepage, https://github.com/oclero/pdfwm
Project-URL: Repository, https://github.com/oclero/pdfwm
Project-URL: Issues, https://github.com/oclero/pdfwm/issues
Keywords: pdf,watermark,batch,cli,filigrane
Classifier: Development Status :: 4 - Beta
Classifier: Intended Audience :: Developers
Classifier: License :: OSI Approved :: MIT License
Classifier: Programming Language :: Python :: 3
Classifier: Programming Language :: Python :: 3.8
Classifier: Programming Language :: Python :: 3.9
Classifier: Programming Language :: Python :: 3.10
Classifier: Programming Language :: Python :: 3.11
Classifier: Programming Language :: Python :: 3.12
Classifier: Topic :: Software Development :: Libraries :: Python Modules
Classifier: Topic :: Utilities
Requires-Python: >=3.8
License-File: LICENSE
Requires-Dist: PyPDF2>=3.0.0
Requires-Dist: reportlab>=4.0.0
Provides-Extra: dev
Requires-Dist: pytest>=7.0.0; extra == "dev"
Requires-Dist: black>=22.0.0; extra == "dev"
Requires-Dist: mypy>=0.990; extra == "dev"
Requires-Dist: ruff>=0.1.0; extra == "dev"
Dynamic: license-file
